hmp_aviel/__init__.py
hmp_aviel/console.py
hmp_aviel/wikipedia.py
hmp_aviel-0.1.0.dist-info/entry_points.txt
hmp_aviel-0.1.0.dist-info/LICENSE
hmp_aviel-0.1.0.dist-info/WHEEL
hmp_aviel-0.1.0.dist-info/METADATA
hmp_aviel-0.1.0.dist-info/RECORD
