Metadata-Version: 2.1
Name: hmp-aviel
Version: 0.1.0
Summary: 
Author: Your Name
Author-email: you@example.com
Requires-Python: >=3.7,<4.0
Classifier: Programming Language :: Python :: 3
Classifier: Programming Language :: Python :: 3.7
Classifier: Programming Language :: Python :: 3.8
Classifier: Programming Language :: Python :: 3.9
Classifier: Programming Language :: Python :: 3.10
Requires-Dist: Pygments (>=2.12.0,<3.0.0)
Requires-Dist: Sphinx (>=4.0.0,<5.0.0)
Requires-Dist: black (>=22.3.0,<23.0.0)
Requires-Dist: click (>=8.1.3,<9.0.0)
Requires-Dist: codecov (>=2.1.12,<3.0.0)
Requires-Dist: coverage[toml] (>=6.4.1,<7.0.0)
Requires-Dist: desert (>=2020.11.18,<2021.0.0)
Requires-Dist: flake8 (>=4.0.1,<5.0.0)
Requires-Dist: flake8-bandit (>=3.0.0,<4.0.0)
Requires-Dist: flake8-black (>=0.3.3,<0.4.0)
Requires-Dist: flake8-bugbear (>=22.6.22,<23.0.0)
Requires-Dist: flake8-import-order (>=0.18.1,<0.19.0)
Requires-Dist: marshmallow (>=3.17.0,<4.0.0)
Requires-Dist: mypy (>=0.961,<0.962)
Requires-Dist: pre-commit (>=2.19.0,<3.0.0)
Requires-Dist: pytest-cov (>=3.0.0,<4.0.0)
Requires-Dist: requests (>=2.28.0,<3.0.0)
Requires-Dist: sphinx-autodoc-typehints (>=1.17,<2.0)
Requires-Dist: typeguard (>=2.13.3,<3.0.0)
Requires-Dist: types-requests (>=2.28.0,<3.0.0)
